[
    {
        "score": 16,
        "responses": {
            "q1": "A. Always, I maintain clear boundaries.",
            "q2": "A. Always, I make it a priority.",
            "q3": "A. Very consistent, I prioritize my physical well-being.",
            "q4": "A. Always, I actively manage stress effectively."
        }
    },
    {
        "score": 16,
        "responses": {
            "q1": "A. Always, I maintain clear boundaries.",
            "q2": "A. Always, I make it a priority.",
            "q3": "A. Very consistent, I prioritize my physical well-being.",
            "q4": "A. Always, I actively manage stress effectively."
        }
    },
    {
        "score": 16,
        "responses": {
            "q1": "A. Always, I maintain clear boundaries.",
            "q2": "A. Always, I make it a priority.",
            "q3": "A. Very consistent, I prioritize my physical well-being.",
            "q4": "A. Always, I actively manage stress effectively."
        }
    }
]